yayawallet_python_sdk/__init__.py
yayawallet_python_sdk/api/__init__.py
yayawallet_python_sdk/api/airtime.py
yayawallet_python_sdk/api/bill.py
yayawallet_python_sdk/api/cash_payment.py
yayawallet_python_sdk/api/device.py
yayawallet_python_sdk/api/equb.py
yayawallet_python_sdk/api/institution.py
yayawallet_python_sdk/api/invitation.py
yayawallet_python_sdk/api/kyc.py
yayawallet_python_sdk/api/lookup.py
yayawallet_python_sdk/api/message_broadcast.py
yayawallet_python_sdk/api/payout.py
yayawallet_python_sdk/api/recurring_contract.py
yayawallet_python_sdk/api/saving.py
yayawallet_python_sdk/api/scheduled.py
yayawallet_python_sdk/api/simulate_transaction.py
yayawallet_python_sdk/api/transaction.py
yayawallet_python_sdk/api/transfer.py
yayawallet_python_sdk/api/user.py
yayawallet_python_sdk/api/utility.py
yayawallet_python_sdk/functions/__init__.py
yayawallet_python_sdk/functions/api_request.py
yayawallet_python_sdk/functions/generate_signature.py
yayawallet_python_sdk/functions/get_api_secret.py
yayawallet_python_sdk/functions/get_time.py
yayawallet_python_sdk/functions/verify.py
yayawallet_python_sdk/serializers/__init__.py
yayawallet_python_sdk/serializers/payout_serializers.py
yayawallet_python_sdk/serializers/user_serializers.py
yayawallet_python_sdk-1.10.3.dist-info/METADATA
yayawallet_python_sdk-1.10.3.dist-info/WHEEL
yayawallet_python_sdk-1.10.3.dist-info/top_level.txt
yayawallet_python_sdk-1.10.3.dist-info/RECORD
