Metadata-Version: 2.4
Name: yayawallet-python-sdk
Version: 1.10.3
Summary: YaYa Wallet Python SDK
Author: YaYa Wallet
Author-email: contact@yayawallet.com
Dynamic: author
Dynamic: author-email
Dynamic: description
Dynamic: description-content-type
Dynamic: summary
